ctrlair/__init__.py
ctrlair/shapes.py
ctrlair/theme.py
ctrlair/utils.py
ctrlair-0.2.1.dist-info/LICENSE
ctrlair-0.2.1.dist-info/METADATA
ctrlair-0.2.1.dist-info/WHEEL
ctrlair-0.2.1.dist-info/top_level.txt
ctrlair-0.2.1.dist-info/RECORD
